sstc-0.1.0.dist-info/METADATA
sstc-0.1.0.dist-info/RECORD
sstc-0.1.0.dist-info/WHEEL
sstc-0.1.0.dist-info/pbr.json
sstc-0.1.0.dist-info/top_level.txt
sstc-0.1.0.dist-info/metadata.json
sstc-0.1.0.dist-info/DESCRIPTION.rst
sstc/__init__.py
sstc/sstc.py
