Metadata-Version: 2.0
Name: sstc
Version: 0.1.0
Summary: Simple torrent client on top of libtorrent rasterbar
Home-page: https://github.com/jcsaaddupuy/sstc
Author: Jean-Christophe Saad-Dupuy
Author-email: jc.saaddupuy@fsfe.org
License: WTFPL
Keywords: sstc
Platform: UNKNOWN
Classifier: Development Status :: 2 - Pre-Alpha
Classifier: Intended Audience :: Developers
Classifier: Natural Language :: English
Classifier: Programming Language :: Python :: 2
Classifier: Programming Language :: Python :: 2.7
Requires-Dist: wheel (>=0.23.0)
Requires-Dist: requests (>=2.3.0)
Requires-Dist: python-libtorrent (>=1.0.3)
